pyfinex/__init__.py
pyfinex/api.py
pyfinex/v1/__init__.py
pyfinex/v1/account.py
pyfinex/v1/funding.py
pyfinex/v1/historical.py
pyfinex/v1/misc.py
pyfinex/v1/orders.py
pyfinex/v1/positions.py
pyfinex/v1/public.py
pyfinex/v2/__init__.py
pyfinex/v2/account.py
pyfinex/v2/alerts.py
pyfinex/v2/funding.py
pyfinex/v2/historical.py
pyfinex/v2/orders.py
pyfinex/v2/positions.py
pyfinex/v2/public.py
pyfinex/v2/user_settings.py
pyfinex-1.0.3.dist-info/METADATA
pyfinex-1.0.3.dist-info/RECORD
pyfinex-1.0.3.dist-info/WHEEL
pyfinex-1.0.3.dist-info/top_level.txt
