Metadata-Version: 2.1
Name: pyfinex
Version: 1.0.3
Summary: Python wrapper for Bitfinex API v1 and v2
Home-page: https://github.com/faberquisque/pyfinex
Author: faberquisque
Author-email: faberquisque@hotmail.com
License: UNKNOWN
Platform: UNKNOWN
Classifier: Programming Language :: Python :: 3
Classifier: License :: OSI Approved :: MIT License
Classifier: Operating System :: OS Independent
